pcluster/__init__.py
pcluster/constants.py
pcluster/imagebuilder_utils.py
pcluster/launch_template_utils.py
pcluster/utils.py
pcluster/api/__init__.py
pcluster/api/converters.py
pcluster/api/encoder.py
pcluster/api/errors.py
pcluster/api/flask_app.py
pcluster/api/typing_utils.py
pcluster/api/util.py
pcluster/api/awslambda/__init__.py
pcluster/api/awslambda/entrypoint.py
pcluster/api/awslambda/serverless_wsgi.py
pcluster/api/controllers/__init__.py
pcluster/api/controllers/cluster_compute_fleet_controller.py
pcluster/api/controllers/cluster_instances_controller.py
pcluster/api/controllers/cluster_logs_controller.py
pcluster/api/controllers/cluster_operations_controller.py
pcluster/api/controllers/common.py
pcluster/api/controllers/image_logs_controller.py
pcluster/api/controllers/image_operations_controller.py
pcluster/api/models/__init__.py
pcluster/api/models/ami_info.py
pcluster/api/models/bad_request_exception_response_content.py
pcluster/api/models/base_model_.py
pcluster/api/models/build_image_bad_request_exception_response_content.py
pcluster/api/models/build_image_request_content.py
pcluster/api/models/build_image_response_content.py
pcluster/api/models/change.py
pcluster/api/models/cloud_formation_resource_status.py
pcluster/api/models/cloud_formation_stack_status.py
pcluster/api/models/cluster_configuration_structure.py
pcluster/api/models/cluster_info_summary.py
pcluster/api/models/cluster_instance.py
pcluster/api/models/cluster_status.py
pcluster/api/models/cluster_status_filtering_option.py
pcluster/api/models/compute_fleet_status.py
pcluster/api/models/config_validation_message.py
pcluster/api/models/conflict_exception_response_content.py
pcluster/api/models/create_cluster_bad_request_exception_response_content.py
pcluster/api/models/create_cluster_request_content.py
pcluster/api/models/create_cluster_response_content.py
pcluster/api/models/delete_cluster_response_content.py
pcluster/api/models/delete_image_response_content.py
aws_parallelcluster-3.14.1.dist-info/METADATA
aws_parallelcluster-3.14.1.dist-info/WHEEL
aws_parallelcluster-3.14.1.dist-info/entry_points.txt
aws_parallelcluster-3.14.1.dist-info/top_level.txt
aws_parallelcluster-3.14.1.dist-info/RECORD
